<?xml version="1.0" encoding="utf-8" ?>
<dwsync>
<file name="cheatsheet.html" server="114.55.27.112//data1/sci/apps/websites/smpss/" local="131123574870000000" remote="131506957030000000" Dst="0" />
<file name="CNAME" server="114.55.27.112//data1/sci/apps/websites/smpss/" local="131123574870000000" remote="131506957030000000" Dst="0" />
<file name="community.html" server="114.55.27.112//data1/sci/apps/websites/smpss/" local="131123574870000000" remote="131506957030000000" Dst="0" />
<file name="design.html" server="114.55.27.112//data1/sci/apps/websites/smpss/" local="131123574870000000" remote="131506957040000000" Dst="0" />
<file name="examples.html" server="114.55.27.112//data1/sci/apps/websites/smpss/" local="131123574870000000" remote="131506957040000000" Dst="0" />
<file name="get-started.html" server="114.55.27.112//data1/sci/apps/websites/smpss/" local="131123574870000000" remote="131506957040000000" Dst="0" />
<file name="icons.html" server="114.55.27.112//data1/sci/apps/websites/smpss/" local="131123574870000000" remote="131506957050000000" Dst="0" />
<file name="icons.yml" server="114.55.27.112//data1/sci/apps/websites/smpss/" local="131123574870000000" remote="131506957050000000" Dst="0" />
<file name="index.html" server="114.55.27.112//data1/sci/apps/websites/smpss/" local="131123574870000000" remote="131506957050000000" Dst="0" />
<file name="license.html" server="114.55.27.112//data1/sci/apps/websites/smpss/" local="131123574870000000" remote="131506957050000000" Dst="0" />
<file name="Makefile" server="114.55.27.112//data1/sci/apps/websites/smpss/" local="131123574870000000" remote="131506957060000000" Dst="0" />
<file name="test.html" server="114.55.27.112//data1/sci/apps/websites/smpss/" local="131123574870000000" remote="131506957060000000" Dst="0" />
<file name="whats-new.html" server="114.55.27.112//data1/sci/apps/websites/smpss/" local="131123574870000000" remote="131506957060000000" Dst="0" />
</dwsync>